llm_dspy/__init__.py
llm_dspy/foo.py
llm_dspy-0.0.1.dist-info/METADATA
llm_dspy-0.0.1.dist-info/WHEEL
llm_dspy-0.0.1.dist-info/licenses/LICENSE
llm_dspy-0.0.1.dist-info/RECORD
