Metadata-Version: 2.4
Name: llm-dspy
Version: 0.0.1
Summary: llm plugin for dspy
Project-URL: Homepage, https://imaurer.github.io/llm-dspy/
Project-URL: Repository, https://github.com/imaurer/llm-dspy
Project-URL: Documentation, https://imaurer.github.io/llm-dspy/
Author-email: Ian Maurer <ian@genomoncology.com>
License-File: LICENSE
Keywords: python
Classifier: Intended Audience :: Developers
Classifier: Programming Language :: Python
Classifier: Programming Language :: Python :: 3
Classifier: Programming Language :: Python :: 3.9
Classifier: Programming Language :: Python :: 3.10
Classifier: Programming Language :: Python :: 3.11
Classifier: Programming Language :: Python :: 3.12
Classifier: Programming Language :: Python :: 3.13
Classifier: Topic :: Software Development :: Libraries :: Python Modules
Requires-Python: <4.0,>=3.9
